expert_doc/__init__.py
expert_doc/doc_parser.py
expert_doc/models.py
expert_doc/pdf_parser.py
expert_doc-0.1.1.dist-info/METADATA
expert_doc-0.1.1.dist-info/WHEEL
expert_doc-0.1.1.dist-info/top_level.txt
expert_doc-0.1.1.dist-info/RECORD
